{
  "cheese":[
    {
      "name":"Grana padana",
      "picture":"food",
      "description":"Lorem ipsum dolor sit amet, consectetur adipisicing elit. Officiis explicabo temporibus est placeat repudiandae unde similique accusamus dolore soluta. Error corporis obcaecati sunt similique eveniet expedita deleniti cumque odio fugiat.",
      "country":{
        "name":"italy",
        "short":"it"
      },
      "tag":[
        "matured"
      ]
    },
    {
      "name":"Gorgonzola",
      "picture":"food",
      "description":"Lorem ipsum dolor sit amet, consectetur adipisicing elit. Quaerat sed eveniet sint, libero quisquam temporibus, voluptatem sapiente debitis ut dolorum numquam blanditiis consectetur illum non nihil. Quod delectus ipsam molestias?",
      "country":{
        "name":"italy",
        "short":"it"
      },
      "tag":[
        "blue",
        "runny"
      ]
    },
    {
      "name":"Brie",
      "picture":"food",
      "description":"Lorem ipsum dolor sit amet, consectetur adipisicing elit. Vero asperiores aut aperiam et sed id, culpa dolore ex labore similique nihil accusamus quo, nostrum, iusto. Nobis, suscipit! Libero, architecto, atque!",
      "country":{
        "name":"france",
        "short":"fr"
      },
      "tag":[
        "runny"
      ]
    },
    {
      "name":"Gammel Dansk",
      "picture":"food",
      "description":"Lorem ipsum dolor sit amet, consectetur adipisicing elit. Reiciendis veritatis eum minima excepturi, asperiores dolores cumque repudiandae molestiae commodi est temporibus aliquid voluptate consequuntur pariatur magni quam quibusdam reprehenderit dolore.",
      "country":{
        "name":"denmark",
        "short":"dk"
      },
      "tag":[
        "medium"
      ]
    },
    {
      "name":"Alpujarra",
      "picture":"food",
      "description":"Lorem ipsum dolor sit amet, consectetur adipisicing elit. Autem, ducimus eligendi enim repellendus eos a neque. Quis ab, non ad quod, aliquam eveniet! Eaque et dolores, sint iste ipsum velit.",
      "country":{
        "name":"spain",
        "short":"es"
      },
      "tag":[
        "matured"
      ]
    },
    {
      "name":"Roquefort",
      "picture":"food",
      "description":"Lorem ipsum dolor sit amet, consectetur adipisicing elit. Recusandae ipsam nulla iste enim sint. Deserunt molestiae cupiditate, odit magni, aliquam voluptatibus a aut maiores molestias, excepturi ad maxime voluptates culpa?",
      "country":{
        "name":"france",
        "short":"fr"
      },
      "tag":[
        "blue",
        "runny"
      ]
    },
    {
      "name":"Camembert",
      "picture":"food",
      "description":"Lorem ipsum dolor sit amet, consectetur adipisicing elit. Possimus voluptatum id illum saepe neque rerum nemo, deserunt placeat labore facere minima repellendus. Soluta porro enim voluptas unde, cum dolor natus.",
      "country":{
        "name":"france",
        "short":"fr"
      },
      "tag":[
        "runny"
      ]
    },
    {
      "name":"Gamle Ole",
      "picture":"food",
      "description":"Lorem ipsum dolor sit amet, consectetur adipisicing elit. Quisquam asperiores inventore facere, libero dolor dignissimos magni, minima officia animi, harum deserunt eius atque! Ratione fugiat harum, unde dolore, nostrum natus.",
      "country":{
        "name":"denmark",
        "short":"dk"
      },
      "tag":[
        "matured"
      ]
    },
    {
      "name":"Pecorino Sardo",
      "picture":"food",
      "description":"Lorem ipsum dolor sit amet, consectetur adipisicing elit. Quisquam asperiores inventore facere, libero dolor dignissimos magni, minima officia animi, harum deserunt eius atque! Ratione fugiat harum, unde dolore, nostrum natus.",
      "country":{
        "name":"italy",
        "short":"it"
      },
      "tag":[
        "matured"
      ]
    },
    {
      "name":"Pecorino Romano",
      "picture":"food",
      "description":"Lorem ipsum dolor sit amet, consectetur adipisicing elit. Totam iure, debitis dolor quo nostrum unde tempora impedit? Blanditiis, ipsum a mollitia beatae, ratione debitis, architecto, iste quo libero reprehenderit veritatis.",
      "country":{
        "name":"italy",
        "short":"it"
      },
      "tag":[
        "matured"
      ]
    }
  ]
}
